parlpy/__init__.py
parlpy/bills/__init__.py
parlpy/bills/bill_details_iterator.py
parlpy/bills/bill_list_fetcher.py
parlpy/bills/bill_votes_fetcher.py
parlpy/bills/summary_fetcher.py
parlpy/mps/__init__.py
parlpy/mps/mp_fetcher.py
parlpy/mps/parties_fetcher.py
parlpy/utils/__init__.py
parlpy/utils/constituency.py
parlpy/utils/dates.py
ParlPy-2.6.0.dist-info/LICENSE.txt
ParlPy-2.6.0.dist-info/METADATA
ParlPy-2.6.0.dist-info/WHEEL
ParlPy-2.6.0.dist-info/top_level.txt
ParlPy-2.6.0.dist-info/RECORD
