Metadata-Version: 2.1
Name: ParlPy
Version: 2.6.0
Summary: API Wrapper and Scraper for UK Parliamentary Bills
Home-page: https://github.com/Litharge/ParlPy
Author: Robert Chambers
Author-email: 1robertchambers@gmail.com
License: UNKNOWN
Platform: UNKNOWN
Classifier: Programming Language :: Python :: 3
Classifier: Operating System :: OS Independent
License-File: LICENSE.txt
Requires-Dist: pandas
Requires-Dist: bs4
Requires-Dist: gcsfs
